jatime/__init__.py
jatime/analyzer.py
jatime/converter.py
jatime/cui.py
jatime/errors.py
jatime/finder.py
jatime/patterns.py
jatime/server.py
jatime/times.py
jatime-0.1.0.dist-info/entry_points.txt
jatime-0.1.0.dist-info/LICENSE
jatime-0.1.0.dist-info/WHEEL
jatime-0.1.0.dist-info/METADATA
jatime-0.1.0.dist-info/RECORD
