Metadata-Version: 2.1
Name: jatime
Version: 0.1.0
Summary: Time expression analyzer for Japanese.
Home-page: https://poyo46.github.io/jatime/
License: Apache-2.0
Keywords: time,japanese
Author: poyo46
Author-email: poyo4rock@gmail.com
Requires-Python: >=3.6,<4.0
Classifier: Development Status :: 3 - Alpha
Classifier: Intended Audience :: Developers
Classifier: Intended Audience :: Information Technology
Classifier: License :: OSI Approved :: Apache Software License
Classifier: Natural Language :: Japanese
Classifier: Operating System :: MacOS :: MacOS X
Classifier: Operating System :: POSIX :: Linux
Classifier: Programming Language :: Python :: 3
Classifier: Programming Language :: Python :: 3.6
Classifier: Programming Language :: Python :: 3.7
Classifier: Programming Language :: Python :: 3.8
Requires-Dist: click (>=7.1.2,<8.0.0)
Requires-Dist: flask (>=1.1.2,<2.0.0)
Project-URL: Repository, https://github.com/poyo46/jatime
